{
    "fluentMethods": true,
    "relationships": [
        {
            "relationshipType": "one-to-many",
            "relationshipName": "relTutMat",
            "otherEntityName": "materie",
            "otherEntityRelationshipName": "relMatTut"
        }
    ],
    "fields": [
        {
            "fieldName": "nome",
            "fieldType": "String"
        },
        {
            "fieldName": "cognome",
            "fieldType": "String"
        },
        {
            "fieldName": "email",
            "fieldType": "String"
        },
        {
            "fieldName": "abilitato",
            "fieldType": "Boolean"
        }
    ],
    "changelogDate": "20180420142055",
    "entityTableName": "tutor",
    "dto": "mapstruct",
    "pagination": "no",
    "service": "serviceImpl",
    "jpaMetamodelFiltering": false
}